dopt/__init__.py
dopt/server.py
dopt/trainer.py
dopt/optimizers/__init__.py
dopt/optimizers/neioptimizer.py
dopt/optimizers/optimizer.py
dopt/synthetic_objective_function/__init__.py
dopt/utils/__init__.py
dopt/utils/general_utils.py
dopt/utils/ssh_utils.py
dopt-0.0.6.dist-info/.ipynb_checkpoints/PKG-INFO-checkpoint
dopt-0.0.6.dist-info/.ipynb_checkpoints/SOURCES-checkpoint.txt
dopt-0.0.6.dist-info/.ipynb_checkpoints/dependency_links-checkpoint.txt
tests/__init__.py
tests/test_optimizer.py
tests/test_trainer.py
dopt-0.0.6.dist-info/LICENSE
dopt-0.0.6.dist-info/METADATA
dopt-0.0.6.dist-info/WHEEL
dopt-0.0.6.dist-info/top_level.txt
dopt-0.0.6.dist-info/RECORD
