Metadata-Version: 2.1
Name: dopt
Version: 0.0.6
Summary: Distributed Optimizer
Home-page: https://github.com/pypa/sampleproject
Author: Tung Tran
Author-email: sontungtran99@gmail.com
Classifier: Programming Language :: Python :: 3
Classifier: License :: OSI Approved :: MIT License
Classifier: Operating System :: OS Independent
Requires-Python: >=3.6
License-File: LICENSE
